{"cameraMode":{"drawMode":0,"name":"Shaded","section":"Shading Mode"},"sceneLighting":true,"audioPlay":false,"sceneViewState":{"m_AlwaysRefresh":false,"showFog":true,"showSkybox":true,"showFlares":true,"showImageEffects":true,"showParticleSystems":true,"showVisualEffectGraphs":true,"m_FxEnabled":true},"in2DMode":false,"pivot":{"x":960.36865234375,"y":539.6443481445313,"z":-0.4013608694076538},"rotation":{"x":0.05709056183695793,"y":0.08077377825975418,"z":-0.004634359385818243,"w":0.9950867295265198},"size":58.88996124267578,"orthographic":false}